{
    "underBoss" : {
        "nickname": "Underboss",
        "description": "The second-in-command, a mastermind of strategy and keeper of order within the organization.",
        "visualDescription": "Dressed in a sharp suit that commands respect and fear, the Underboss stands confidently, hand in jacket, hinting at concealed strength.",
        "imagePath": "underboss.png",
        "Health": 80,
        "Power": 7,
        "Attack Power": 6,
        "Defense Power": 7,
        "Business Skills": 9,
        "Building Skills": 4,
        "Healing Skills": 3,
        "Research Skills": 5,
        "MartialArts Skills": 6,
        "Sword Skills": 4,
        "Gun Skills": 8,
        "Vision": 7,
        "Stealth": 6
    },    
    "characters": [
        {
            "nickname": "Night Specter",
            "description": "An elite operative skilled in nocturnal missions, utilizing cutting-edge technology to become nearly invisible.",
            "visualDescription": "Clad in a high-tech stealth suit with night vision goggles and a silenced sniper.",
            "imagePath": "night_specter.png",
            "Health": 100,
            "Power": 7,
            "Attack Power": 8,
            "Defense Power": 6,
            "Business Skills": 3,
            "Building Skills": 4,
            "Healing Skills": 5,
            "Research Skills": 9,
            "MartialArts Skills": 4,
            "Sword Skills": 3,
            "Gun Skills": 8,
            "Vision": 7,
            "Stealth": 9,
            "Cost": 10
        },
        {
            "nickname": "Tech Warden",
            "description": "A guardian of peace equipped with the latest defensive technology and crowd control gadgets.",
            "visualDescription": "Wearing a suit of modular armor equipped with shields and non-lethal deterrents.",
            "imagePath": "tech_warden.png",
            "Health": 110,
            "Power": 6,
            "Attack Power": 5,
            "Defense Power": 9,
            "Business Skills": 4,
            "Building Skills": 5,
            "Healing Skills": 3,
            "Research Skills": 7,
            "MartialArts Skills": 3,
            "Sword Skills": 2,
            "Gun Skills": 6,
            "Vision": 8,
            "Stealth": 5,
            "Cost": 8
        },
        {
            "nickname": "Drone Ranger",
            "description": "A master in unmanned warfare, commanding a fleet of drones for reconnaissance and attack.",
            "visualDescription": "Equipped with a lightweight tactical suit and a portable drone command station.",
            "imagePath": "drone_ranger.png",
            "Health": 90,
            "Power": 7,
            "Attack Power": 7,
            "Defense Power": 5,
            "Business Skills": 6,
            "Building Skills": 7,
            "Healing Skills": 4,
            "Research Skills": 8,
            "MartialArts Skills": 2,
            "Sword Skills": 1,
            "Gun Skills": 7,
            "Vision": 10,
            "Stealth": 10,
            "Cost": 12
        },
        {
            "nickname": "Cyber Sapper",
            "description": "An expert in electronic warfare, capable of hacking and disabling enemy systems with ease.",
            "visualDescription": "Sporting a utility vest brimming with tools and gadgets, eyes focused behind advanced AR goggles.",
            "imagePath": "cyber_sapper.png",
            "Health": 85,
            "Power": 5,
            "Attack Power": 4,
            "Defense Power": 6,
            "Business Skills": 5,
            "Building Skills": 8,
            "Healing Skills": 4,
            "Research Skills": 10,
            "MartialArts Skills": 3,
            "Sword Skills": 2,
            "Gun Skills": 5,
            "Vision": 10,
            "Stealth": 6,
            "Cost": 9
        },
        {
            "nickname": "Gadgeteer Ghost",
            "description": "A covert operative specializing in the use of gadgets and traps to outmaneuver and outsmart the enemy.",
            "visualDescription": "Dressed in a sleek, gadget-laden suit, ready to deploy a variety of high-tech traps and tools.",
            "imagePath": "gadgeteer_ghost.png",
            "Health": 95,
            "Power": 8,
            "Attack Power": 6,
            "Defense Power": 7,
            "Business Skills": 1,
            "Building Skills": 1,
            "Healing Skills": 1,
            "Research Skills": 2,
            "MartialArts Skills": 9,
            "Sword Skills": 2,
            "Gun Skills": 10,
            "Vision": 10,
            "Stealth": 10,
            "Cost": 11
        },        
        {
            "nickname": "Iron Sentinel",
            "description": "A steadfast guardian known for unbreakable defense and strategic prowess on the battlefield.",
            "visualDescription": "Clad in heavy, ironclad armor with a towering shield and battle-worn sword.",
            "imagePath": "iron_sentinel.png",
            "Health": 110,
            "Power": 5,
            "Attack Power": 5,
            "Defense Power": 10,
            "Building Skills": 7,
            "Healing Skills": 3,
            "Research Skills": 5,
            "MartialArts Skills": 4,
            "Sword Skills": 6,
            "Gun Skills": 3,
            "Vision": 5,
            "Stealth": 2,
            "Cost": 8
        },
        {
            "nickname": "Crimson Rogue",
            "description": "A notorious mercenary with a penchant for high-risk, high-reward missions.",
            "visualDescription": "Wears a crimson cloak, with a sly grin, dual daggers at the ready.",
            "imagePath": "crimson_rogue.png",
            "Health": 70,
            "Power": 8,
            "Attack Power": 9,
            "Defense Power": 4,
            "Business Skills": 6,
            "Building Skills": 2,
            "Healing Skills": 4,
            "Research Skills": 3,
            "MartialArts Skills": 7,
            "Sword Skills": 8,
            "Gun Skills": 5,
            "Vision": 7,
            "Stealth": 9,
            "Cost": 9
        },
        {
            "nickname": "Arcane Scholar",
            "description": "A wise mage who has mastered the ancient arts, blending magic and knowledge to outwit foes.",
            "visualDescription": "Cloaked in an aura of mystery, holding an ornate staff pulsing with arcane energy.",
            "imagePath": "arcane_scholar.png",
            "Health": 60,
            "Power": 9,
            "Attack Power": 4,
            "Defense Power": 3,
            "Business Skills": 8,
            "Building Skills": 2,
            "Healing Skills": 9,
            "Research Skills": 10,
            "MartialArts Skills": 2,
            "Sword Skills": 3,
            "Gun Skills": 1,
            "Vision": 9,
            "Stealth": 4,
            "Cost": 9
        },
        {
            "nickname": "Dread Pirate",
            "description": "A fearsome pirate lord, infamous across the seven seas for his ruthlessness and cunning.",
            "visualDescription": "Adorned in a tricorn hat, a hook for a hand, and a gaze as cold as the ocean's depths.",
            "imagePath": "dread_pirate.png",
            "Health": 95,
            "Power": 6,
            "Attack Power": 7,
            "Defense Power": 6,
            "Business Skills": 7,
            "Building Skills": 3,
            "Healing Skills": 2,
            "Research Skills": 4,
            "MartialArts Skills": 7,
            "Sword Skills": 9,
            "Gun Skills": 8,
            "Vision": 7,
            "Stealth": 5,
            "Cost": 9
        },
        {
            "nickname": "Beast Tamer",
            "description": "A wild wanderer who has forged an unbreakable bond with the beasts of the land.",
            "visualDescription": "Carries the look of the wild with furs and bones, with piercing eyes that command the respect of beasts.",
            "imagePath": "beast_tamer.png",
            "Health": 100,
            "Power": 7,
            "Attack Power": 6,
            "Defense Power": 8,
            "Business Skills": 5,
            "Building Skills": 4,
            "Healing Skills": 7,
            "Research Skills": 3,
            "MartialArts Skills": 5,
            "Sword Skills": 4,
            "Gun Skills": 2,
            "Vision": 6,
            "Stealth": 8,
            "Cost": 7
        },        
        {
            "nickname": "Shadow Blade",
            "description": "A Stealthy warrior of the night.",
            "visualDescription": "Wears a dark cloak and carries twin blades",
            "imagePath": "shadowNinj.png",
            "Health": 100,
            "Power": 7,
            "Attack Power": 9,
            "Defense Power": 6,
            "Business Skills": 2,
            "Building Skills": 3,
            "Healing Skills": 4,
            "Research Skills": 2,
            "MartialArts Skills": 8,
            "Sword Skills": 9,
            "Gun Skills": 3,
            "Vision": 7,
            "Stealth": 9,
            "Cost": 3
        },
        {
            "nickname": "Mystic Healer",
            "description": "A gentle soul with Powerful healing abilities.",
            "visualDescription": "Radiant attire with a staff that glows with a healing aura",
            "imagePath": "healerAour.png",
            "Health": 80,
            "Power": 4,
            "Attack Power": 3,
            "Defense Power": 5,
            "Business Skills": 6,
            "Building Skills": 4,
            "Healing Skills": 10,
            "Research Skills": 7,
            "MartialArts Skills": 2,
            "Sword Skills": 1,
            "Gun Skills": 1,
            "Vision": 8,
            "Stealth": 3,
            "Cost": 7
        },
        {
            "nickname": "Tribal Mystic",
            "description": "An enigmatic guardian of ancient secrets, shrouded in tribal mystique.",
            "visualDescription": "Cloaked in a hood adorned with tribal patterns and a face obscured by shadow, carrying arrows on the back, and holding a weapon.",
            "imagePath": "bower.png",
            "Health": 85,
            "Power": 7,
            "Attack Power": 8,
            "Defense Power": 6,
            "Business Skills": 3,
            "Building Skills": 4,
            "Healing Skills": 5,
            "Research Skills": 7,
            "MartialArts Skills": 6,
            "Sword Skills": 7,
            "Gun Skills": 5,
            "Vision": 8,
            "Stealth": 10,
            "Cost": 6
        },
        {
            "nickname": "Hazard Hawk",
            "description": "A tactical operative skilled in navigating and neutralizing dangerous territories.",
            "visualDescription": "Equipped with a tactical helmet, night Vision goggles, and a gas mask. Dressed in combat gear suited for hazardous environments.",
            "imagePath": "soljeri.png",
            "Health": 90,
            "Power": 6,
            "Attack Power": 7,
            "Defense Power": 8,
            "Business Skills": 2,
            "Building Skills": 3,
            "Healing Skills": 4,
            "Research Skills": 5,
            "MartialArts Skills": 6,
            "Sword Skills": 2,
            "Gun Skills": 9,
            "Vision": 10,
            "Stealth": 5,
            "Cost": 6
        },
        {
            "nickname": "Venom Stalker",
            "description": "A fearsome predator from the depths of the Shadow Marshes, known for its lethal venom and terrifying speed.",
            "visualDescription": "An imposing figure with a chitinous exoskeleton, multiple eyes that gleam in the dark, and razor-sharp mandibles.",
            "imagePath": "maints.png",
            "Health": 120,
            "Power": 8,
            "Attack Power": 9,
            "Defense Power": 7,
            "Business Skills": 1,
            "Building Skills": 2,
            "Healing Skills": 3,
            "Research Skills": 2,
            "MartialArts Skills": 0,
            "Sword Skills": 0,
            "Gun Skills": 0,
            "Vision": 8,
            "Stealth": 7,
            "Cost": 2
        }
    ]
}